mongo_connect/__init__.py
mongo_connect/mongo_crud.py
mongodb_crud_automation-0.0.13.dist-info/LICENSE
mongodb_crud_automation-0.0.13.dist-info/METADATA
mongodb_crud_automation-0.0.13.dist-info/WHEEL
mongodb_crud_automation-0.0.13.dist-info/top_level.txt
mongodb_crud_automation-0.0.13.dist-info/RECORD
