Metadata-Version: 2.1
Name: mongodb_crud_automation
Version: 0.0.13
Summary: CRUD operations for MongoDB
Home-page: https://github.com/Minali0/mongodbconnectorpkg
Author: Minali0
Author-email: minali.jain@seaflux.tech
License: MIT
Project-URL: Bug Tracker, https://github.com/Minali0/mongodbconnectorpkg/issues
Classifier: Programming Language :: Python :: 3.11
Classifier: Operating System :: OS Independent
License-File: LICENSE
Requires-Dist: pymongo
Requires-Dist: dnspython
Requires-Dist: pandas
Requires-Dist: numpy
Requires-Dist: ensure
Requires-Dist: tox
Provides-Extra: testing
Requires-Dist: pytest>=7.1.3; extra == "testing"
Requires-Dist: mypy>=0.971; extra == "testing"
Requires-Dist: flake8>=5.0.4; extra == "testing"
Requires-Dist: black>=22.8.0; extra == "testing"
